superhelp/__init__.py
superhelp/ansi_tables.json
superhelp/code_execution.py
superhelp/conf.py
superhelp/download_stats.py
superhelp/gen_utils.py
superhelp/helper.py
superhelp/lint_conf.py
superhelp/messages.py
superhelp/name_utils.py
superhelp/utils.py
superhelp/ast_funcs/__init__.py
superhelp/ast_funcs/general.py
superhelp/ast_funcs/versioned_gen.py
superhelp/ast_funcs/versioned_nums.py
superhelp/displayers/cli_displayer.py
superhelp/displayers/html_displayer.py
superhelp/displayers/md_displayer.py
superhelp/formatters/__init__.py
superhelp/formatters/cli_formatter.py
superhelp/formatters/html_formatter.py
superhelp/formatters/md_formatter.py
superhelp/formatters/cli_extras/__init__.py
superhelp/formatters/cli_extras/ansi_printer.py
superhelp/formatters/cli_extras/cli_colour.py
superhelp/formatters/cli_extras/cli_conf.py
superhelp/formatters/cli_extras/cli_utils.py
superhelp/formatters/cli_extras/md2cli.py
superhelp/formatters/cli_extras/tag_formatting.py
superhelp/helpers/__init__.py
superhelp/helpers/class_help.py
superhelp/helpers/context_manager_help.py
superhelp/helpers/dataclass_help.py
superhelp/helpers/decorator_help.py
superhelp/helpers/dict_help.py
superhelp/helpers/enumerate_help.py
superhelp/helpers/exception_help.py
superhelp/helpers/for_help.py
superhelp/helpers/func_help.py
superhelp/helpers/if_else_help.py
superhelp/helpers/import_help.py
superhelp/helpers/lambda_help.py
superhelp/helpers/lint_help.py
superhelp/helpers/list_help.py
superhelp/helpers/listcomp_help.py
superhelp/helpers/magic_num_help.py
superhelp/helpers/name_help.py
superhelp/helpers/named_tuple_help.py
superhelp/helpers/nested_help.py
superhelp/helpers/num_help.py
superhelp/helpers/operator_help.py
superhelp/helpers/packing_help.py
superhelp/helpers/pathlib_help.py
superhelp/helpers/print_help.py
superhelp/helpers/regex_help.py
superhelp/helpers/set_help.py
superhelp/helpers/shared_messages.py
superhelp/helpers/sorting_reversing_help.py
superhelp/helpers/str_help.py
superhelp-1.9.5.dist-info/LICENSE
superhelp-1.9.5.dist-info/METADATA
superhelp-1.9.5.dist-info/WHEEL
superhelp-1.9.5.dist-info/entry_points.txt
superhelp-1.9.5.dist-info/top_level.txt
superhelp-1.9.5.dist-info/RECORD
