Metadata-Version: 2.1
Name: superhelp
Version: 1.9.5
Summary: SuperHELP - Help for Humans!
Home-page: https://github.com/grantps/superhelp
Author: Grant Paton-Simpson
Author-email: grant@p-s.co.nz
License: MIT
Classifier: Development Status :: 5 - Production/Stable
Classifier: Intended Audience :: Developers
Classifier: Intended Audience :: Information Technology
Classifier: Intended Audience :: End Users/Desktop
Classifier: Programming Language :: Python :: 3.11
Classifier: Programming Language :: Python :: 3.12
Classifier: Operating System :: OS Independent
Classifier: Topic :: Education
Classifier: Topic :: Software Development :: Testing
Classifier: Topic :: Education :: Computer Aided Instruction (CAI)
Requires-Python: >=3.11
License-File: LICENSE
Requires-Dist: Markdown >=3.2.1
Requires-Dist: PyYAML >=5.3.1
Requires-Dist: Pygments >=2.6.1
Requires-Dist: astpath >=0.9.1
Requires-Dist: cssselect >=1.1.0
Requires-Dist: flake8 >=3.5
Requires-Dist: lxml >=4.5.0
Requires-Dist: tabulate >=0.8.7
